ddompack/ErrorsBigList.dat
ddompack/__init__.py
ddompack/chain4b.txt
ddompack/ddomsamp.py
ddompack-0.2.6.dist-info/METADATA
ddompack-0.2.6.dist-info/WHEEL
ddompack-0.2.6.dist-info/top_level.txt
ddompack-0.2.6.dist-info/RECORD
