Metadata-Version: 2.1
Name: ddompack
Version: 0.2.6
Summary: DDO
Home-page: 
Author: Peter Shternin
Author-email: pshternin@gmail.com
License: MIT
